{
  "repository": "yagooyarzabaldev-ops/specbridge-v3",
  "branch": "master",
  "attempted": true,
  "applied": false,
  "required_status_checks_requested": {
    "strict": true,
    "contexts": [
      "test"
    ]
  },
  "enforce_admins_requested": true,
  "read_attempt": {
    "command": "gh api repos/yagooyarzabaldev-ops/specbridge-v3/branches/master/protection",
    "exit_code": 1,
    "http_status": 403,
    "message": "Upgrade to GitHub Pro or make this repository public to enable this feature.",
    "documentation_url": "https://docs.github.com/rest/branches/branch-protection#get-branch-protection"
  },
  "write_attempt": {
    "command": "gh api --method PUT repos/yagooyarzabaldev-ops/specbridge-v3/branches/master/protection --input <temp-json>",
    "exit_code": 1,
    "http_status": 403,
    "message": "Upgrade to GitHub Pro or make this repository public to enable this feature.",
    "documentation_url": "https://docs.github.com/rest/branches/branch-protection#update-branch-protection"
  },
  "policy_result": "Public repository visibility change is blocked by the execution contract. The branch protection blocker is therefore external to implementation and requires either GitHub Pro for the private repository or an explicit future policy decision to change visibility.",
  "captured_at": "2026-06-26T04:59:20Z"
}
